splurge_sql_runner/__init__.py
splurge_sql_runner/__main__.py
splurge_sql_runner/cli.py
splurge_sql_runner/cli_output.py
splurge_sql_runner/exceptions.py
splurge_sql_runner/main.py
splurge_sql_runner/result_models.py
splurge_sql_runner/security.py
splurge_sql_runner/sql_helper.py
splurge_sql_runner/_vendor/splurge_exceptions/__init__.py
splurge_sql_runner/_vendor/splurge_exceptions/__main__.py
splurge_sql_runner/_vendor/splurge_exceptions/cli.py
splurge_sql_runner/_vendor/splurge_exceptions/core/__init__.py
splurge_sql_runner/_vendor/splurge_exceptions/core/base.py
splurge_sql_runner/_vendor/splurge_exceptions/core/exceptions.py
splurge_sql_runner/_vendor/splurge_exceptions/formatting/__init__.py
splurge_sql_runner/_vendor/splurge_exceptions/formatting/message.py
splurge_sql_runner/_vendor/splurge_pub_sub/__init__.py
splurge_sql_runner/_vendor/splurge_pub_sub/__main__.py
splurge_sql_runner/_vendor/splurge_pub_sub/cli.py
splurge_sql_runner/_vendor/splurge_pub_sub/constants.py
splurge_sql_runner/_vendor/splurge_pub_sub/decorators.py
splurge_sql_runner/_vendor/splurge_pub_sub/errors.py
splurge_sql_runner/_vendor/splurge_pub_sub/exceptions.py
splurge_sql_runner/_vendor/splurge_pub_sub/filters.py
splurge_sql_runner/_vendor/splurge_pub_sub/message.py
splurge_sql_runner/_vendor/splurge_pub_sub/pubsub.py
splurge_sql_runner/_vendor/splurge_pub_sub/pubsub_aggregator.py
splurge_sql_runner/_vendor/splurge_pub_sub/pubsub_solo.py
splurge_sql_runner/_vendor/splurge_pub_sub/types.py
splurge_sql_runner/_vendor/splurge_pub_sub/utility.py
splurge_sql_runner/_vendor/splurge_pub_sub/_vendor/splurge_exceptions/__init__.py
splurge_sql_runner/_vendor/splurge_pub_sub/_vendor/splurge_exceptions/__main__.py
splurge_sql_runner/_vendor/splurge_pub_sub/_vendor/splurge_exceptions/cli.py
splurge_sql_runner/_vendor/splurge_pub_sub/_vendor/splurge_exceptions/core/__init__.py
splurge_sql_runner/_vendor/splurge_pub_sub/_vendor/splurge_exceptions/core/base.py
splurge_sql_runner-2025.8.0.dist-info/licenses/LICENSE
splurge_sql_runner-2025.8.0.dist-info/METADATA
splurge_sql_runner-2025.8.0.dist-info/WHEEL
splurge_sql_runner-2025.8.0.dist-info/entry_points.txt
splurge_sql_runner-2025.8.0.dist-info/top_level.txt
splurge_sql_runner-2025.8.0.dist-info/RECORD
