Metadata-Version: 2.4
Name: splurge-sql-runner
Version: 2025.8.0
Summary: A Python utility for executing SQL files against databases with support for multiple statements, comments, and pretty-printed results
Author: Jim Schilling
Maintainer: Jim Schilling
License-Expression: MIT
Project-URL: Homepage, https://github.com/jim-schilling/splurge-sql-runner
Project-URL: Documentation, https://github.com/jim-schilling/splurge-sql-runner#readme
Project-URL: Repository, https://github.com/jim-schilling/splurge-sql-runner.git
Project-URL: Issues, https://github.com/jim-schilling/splurge-sql-runner/issues
Project-URL: Changelog, https://github.com/jim-schilling/splurge-sql-runner/blob/main/README.md#changelog
Keywords: sql,database,cli,sqlalchemy,sqlite,postgresql,mysql
Classifier: Development Status :: 4 - Beta
Classifier: Intended Audience :: Developers
Classifier: Intended Audience :: System Administrators
Classifier: Operating System :: OS Independent
Classifier: Programming Language :: Python :: 3
Classifier: Programming Language :: Python :: 3.10
Classifier: Programming Language :: Python :: 3.11
Classifier: Programming Language :: Python :: 3.12
Classifier: Programming Language :: Python :: 3.13
Classifier: Topic :: Database
Classifier: Topic :: Software Development :: Libraries :: Python Modules
Classifier: Topic :: Utilities
Classifier: Environment :: Console
Classifier: Typing :: Typed
Requires-Python: >=3.10
License-File: LICENSE
Requires-Dist: sqlalchemy>=2.0.42
Requires-Dist: sqlparse>=0.5.3
Requires-Dist: tabulate>=0.9.0
Provides-Extra: dev
Requires-Dist: pytest>=8.4.1; extra == "dev"
Requires-Dist: pytest-cov>=6.2.1; extra == "dev"
Requires-Dist: pytest-xdist>=3.8.0; extra == "dev"
Requires-Dist: pytest-mock>=3.15.1; extra == "dev"
Requires-Dist: mypy>=1.18.2; extra == "dev"
Requires-Dist: pre-commit>=4.3.0; extra == "dev"
Requires-Dist: ruff>=0.12.7; extra == "dev"
Provides-Extra: test
Requires-Dist: pytest>=8.4.1; extra == "test"
Requires-Dist: pytest-cov>=6.2.1; extra == "test"
Requires-Dist: pytest-xdist>=3.8.0; extra == "test"
Provides-Extra: lint
Requires-Dist: mypy>=1.18.2; extra == "lint"
Requires-Dist: ruff>=0.12.7; extra == "lint"
Dynamic: license-file
